logfilenamer
