Metadata-Version: 1.0
Name: logfilenamer
Version: 0.5.0
Summary: Name log files using Mosaiq exports.
Home-page: UNKNOWN
Author: Simon Biggs
Author-email: mail@simonbiggs.net
License: AGPL3+
Platform: UNKNOWN
